nonebot_plugin_deepseek/__init__.py
nonebot_plugin_deepseek/_types.py
nonebot_plugin_deepseek/apis/__init__.py
nonebot_plugin_deepseek/apis/request.py
nonebot_plugin_deepseek/cli/__init__.py
nonebot_plugin_deepseek/cli/__main__.py
nonebot_plugin_deepseek/cli/plugins/__init__.py
nonebot_plugin_deepseek/cli/plugins/tts.py
nonebot_plugin_deepseek/compat.py
nonebot_plugin_deepseek/config.py
nonebot_plugin_deepseek/exception.py
nonebot_plugin_deepseek/extension.py
nonebot_plugin_deepseek/function_call/__init__.py
nonebot_plugin_deepseek/function_call/builtins/__init__.py
nonebot_plugin_deepseek/function_call/builtins/website_summary.py
nonebot_plugin_deepseek/function_call/registry.py
nonebot_plugin_deepseek/hook.py
nonebot_plugin_deepseek/log.py
nonebot_plugin_deepseek/placehold_prompt.py
nonebot_plugin_deepseek/resources/tts_models.css
nonebot_plugin_deepseek/schemas/__init__.py
nonebot_plugin_deepseek/schemas/balance.py
nonebot_plugin_deepseek/schemas/chat.py
nonebot_plugin_deepseek/schemas/logprobs.py
nonebot_plugin_deepseek/schemas/message.py
nonebot_plugin_deepseek/schemas/tts.py
nonebot_plugin_deepseek/schemas/usage.py
nonebot_plugin_deepseek/utils.py
nonebot_plugin_deepseek/version.py
nonebot_plugin_deepseek-0.2.0.dist-info/WHEEL
nonebot_plugin_deepseek-0.2.0.dist-info/entry_points.txt
nonebot_plugin_deepseek-0.2.0.dist-info/METADATA
nonebot_plugin_deepseek-0.2.0.dist-info/RECORD
