Metadata-Version: 2.3
Name: nonebot-plugin-deepseek
Version: 0.2.0
Summary: NoneBot DeepSeek 插件。接入 DeepSeek 模型，提供智能对话与问答功能
Keywords: 
Author: KomoriDev 
Author-email: KomoriDev  <mute231010@gmail.com>
License: MIT
Requires-Dist: nonebot2>=2.4.1
Requires-Dist: nonebot-plugin-alconna>=0.57.0
Requires-Dist: httpx[http2]>=0.28.1
Requires-Dist: beautifulsoup4>=4.12.3
Requires-Dist: nonebot-plugin-localstore>=0.7.3
Requires-Dist: cli-lite>=0.10.2
Requires-Dist: pydantic-yaml>=1.4.0 ; extra == 'full'
Requires-Dist: nonebot-plugin-uninfo>=0.7.0 ; extra == 'full'
Requires-Dist: nonebot-plugin-htmlrender>=0.5.1 ; extra == 'full'
Requires-Dist: nonebot-plugin-htmlrender>=0.5.1 ; extra == 'image'
Requires-Dist: pytest>=8.3.4 ; extra == 'test'
Requires-Dist: nonebug>=0.4.3 ; extra == 'test'
Requires-Dist: pytest-asyncio>=0.25.3 ; extra == 'test'
Requires-Dist: nonebot-plugin-uninfo>=0.7.0 ; extra == 'uninfo'
Requires-Dist: pydantic-yaml>=1.4.0 ; extra == 'yaml'
Requires-Python: >=3.9
Project-URL: homepage, https://github.com/KomoriDev/nonebot-plugin-deepseek
Project-URL: repository, https://github.com/KomoriDev/nonebot-plugin-deepseek
Provides-Extra: full
Provides-Extra: image
Provides-Extra: test
Provides-Extra: uninfo
Provides-Extra: yaml
